leankit/__init__.py
leankit/config.py
leankit/connector.py
leankit/kanban.py
leankit-1.2.3.dist-info/DESCRIPTION.rst
leankit-1.2.3.dist-info/METADATA
leankit-1.2.3.dist-info/RECORD
leankit-1.2.3.dist-info/WHEEL
leankit-1.2.3.dist-info/metadata.json
leankit-1.2.3.dist-info/top_level.txt
